{
    "local_wst_warn_info": [
        {
            "basin_no": "1630",
            "st_no": "W1771301",
            "st_name": "民生橋",
            "river": "菜寮溪",
            "info": "26.94",
            "alert_level": "未達警戒",
            "warn_info": "水位目前26.94公尺",
            "date": "2018\/07\/09 19:10",
            "change": "-0.01"
        },
        {
            "basin_no": "1630",
            "st_no": "W1772403",
            "st_name": "龍山漁港",
            "river": "劉厝排水",
            "info": "0.61",
            "alert_level": "未達警戒",
            "warn_info": "水位目前0.61公尺,距警戒水位尚有1.09公尺,行動值為1.19公尺",
            "date": "2018\/07\/09 19:10",
            "change": "0.03"
        }
    ]
}