{
    "local_wst_warn_info": [
        {
            "basin_no": "1660",
            "st_no": "W1771709",
            "st_name": "港尾溝溪分洪匯流口",
            "river": "港尾溝排水",
            "info": "4.07",
            "alert_level": "未達警戒",
            "warn_info": "水位目前4.07公尺,距警戒水位尚有4.43公尺,行動值為-999公尺",
            "date": "2017\/08\/03 08:30",
            "change": "0.00"
        },
        {
            "basin_no": "1660",
            "st_no": "W1771711",
            "st_name": "仁德滯洪南池",
            "river": "三爺溪排水",
            "info": "1.84",
            "alert_level": "未達警戒",
            "warn_info": "水位目前1.84公尺",
            "date": "2017\/08\/03 08:30",
            "change": "0.00"
        }
    ]
}